{"cameraMode":{"drawMode":0,"name":"Shaded","section":"Shading Mode"},"sceneLighting":false,"audioPlay":false,"sceneViewState":{"showFog":true,"showMaterialUpdate":false,"showSkybox":false,"showFlares":true,"showImageEffects":true,"showParticleSystems":true},"in2DMode":false,"pivot":{"x":6.926123142242432,"y":0.7165682911872864,"z":6.539285659790039},"rotation":{"x":-0.11720824986696243,"y":-0.6860634088516235,"z":0.11339512467384339,"w":-0.7090773582458496},"size":2.8578836917877199,"orthographic":false}